tinge/__init__.py
tinge/color_print.py
tinge/specials.py
tinge/utils.py
Tinge-0.0.7.dist-info/LICENSE
Tinge-0.0.7.dist-info/METADATA
Tinge-0.0.7.dist-info/WHEEL
Tinge-0.0.7.dist-info/top_level.txt
Tinge-0.0.7.dist-info/RECORD
