Metadata-Version: 2.1
Name: Tinge
Version: 0.0.7
Summary: Colored text for terminal
Home-page: https://github.com/g-paras/tinge
Author: Paras Gupta
Author-email: guptaparas039@gmail.com
License: MIT
Platform: UNKNOWN
Classifier: License :: OSI Approved :: MIT License
Classifier: Programming Language :: Python
Classifier: Programming Language :: Python :: 3
Classifier: Environment :: Console
Classifier: Operating System :: OS Independent
Classifier: Topic :: Terminals
Classifier: Topic :: Text Processing
Classifier: Topic :: Utilities
Requires-Python: >=3.5
License-File: LICENSE
